{
  "friends" : [{
    "name" : "angelababy",
    "url" : "http://tp3.sinaimg.cn/1642351362/180/5728706692/0",
    "title" : "颜值担当师"
  }, {
    "name" : "倪妮",
    "url" : "http://tp2.sinaimg.cn/2554404125/180/5731656158/0",
    "title" : "颜值担当师"
  }, {
    "name" : "迪丽热巴",
    "url" : "http://tp1.sinaimg.cn/1669879400/180/5634634197/0",
    "title" : "颜值担当师"
  }, {
    "name" : "张萌",
    "url" : "http://tp1.sinaimg.cn/1222062284/180/5712888810/0",
    "title" : "颜值担当师"
  }, {
    "name" : "朴信惠",
    "url" : "http://tp3.sinaimg.cn/1864923034/180/5738654515/0",
    "title" : "颜值担当师"
  }, {
    "name" : "郭碧婷",
    "url" : "http://tp4.sinaimg.cn/1729370543/180/5681988346/0",
    "title" : "颜值担当师"
  } ],
  "profile" : {
    "company" : "MEITUAN",
    "name" : "有田十三"
  }
}
